pybitrix24/__init__.py
pybitrix24/bitrix24.py
pybitrix24/exceptions.py
pybitrix24/requester.py
tests/__init__.py
tests/automation.py
tests/test_e2e.py
tests/test_unit.py
pybitrix24-1.1.0.dist-info/LICENSE.txt
pybitrix24-1.1.0.dist-info/METADATA
pybitrix24-1.1.0.dist-info/WHEEL
pybitrix24-1.1.0.dist-info/top_level.txt
pybitrix24-1.1.0.dist-info/RECORD
