Metadata-Version: 2.1
Name: pybitrix24
Version: 1.1.0
Summary: The simplest zero dependency polyversion Python library for Bitrix24 REST API.
Home-page: https://github.com/yarbshk/pybitrix24
Author: Yurii Rabeshko
Author-email: yurii.rabeshko@mail.com
License: MIT
Keywords: bitrix24 rest api client sdk library
Platform: any
Classifier: Development Status :: 5 - Production/Stable
Classifier: Intended Audience :: Developers
Classifier: License :: OSI Approved :: MIT License
Classifier: Natural Language :: English
Classifier: Programming Language :: Python :: 2.7
Classifier: Programming Language :: Python :: 3.5
Classifier: Programming Language :: Python :: 3.6
Classifier: Programming Language :: Python :: 3.7
Classifier: Programming Language :: Python :: 3.8
Classifier: Topic :: Software Development :: Libraries :: Python Modules
Requires-Python: >=2.7
License-File: LICENSE.txt
